vtpl_api/__init__.py
vtpl_api/api_client.py
vtpl_api/configuration.py
vtpl_api/exceptions.py
vtpl_api/rest.py
vtpl_api/api/__init__.py
vtpl_api/api/engines_api.py
vtpl_api/models/__init__.py
vtpl_api/models/anpr_event.py
vtpl_api/models/anpr_events_response.py
vtpl_api/models/atccs_event.py
vtpl_api/models/atccs_events_response.py
vtpl_api/models/attire.py
vtpl_api/models/capabilities_response.py
vtpl_api/models/capability.py
vtpl_api/models/capability_type.py
vtpl_api/models/central_face_database.py
vtpl_api/models/central_face_database_response.py
vtpl_api/models/clip.py
vtpl_api/models/clips_response.py
vtpl_api/models/color.py
vtpl_api/models/command.py
vtpl_api/models/commands.py
vtpl_api/models/config.py
vtpl_api/models/crowd_abnormality_event.py
vtpl_api/models/crowd_abnormality_events_response.py
vtpl_api/models/crowd_dispersion_event.py
vtpl_api/models/crowd_dispersion_events_response.py
vtpl_api/models/crowd_formation_event.py
vtpl_api/models/crowd_formation_events_response.py
vtpl_api/models/default_response.py
vtpl_api/models/destination_end_point.py
vtpl_api/models/destination_end_point_destination_list.py
vtpl_api/models/destination_type.py
vtpl_api/models/destination_type_with_caption.py
vtpl_api/models/driver_on_call_event.py
vtpl_api/models/driver_on_call_events_response.py
vtpl_api/models/engine.py
vtpl_api/models/engine_status_command.py
vtpl_api/models/engine_task.py
vtpl_api/models/engine_task_line_setting.py
vtpl_api/models/engine_task_zone_setting.py
vtpl_api/models/engine_tasks_response.py
vtpl_api/models/engines_response.py
vtpl_api/models/event.py
vtpl_api/models/event_details.py
vtpl_api/models/event_snaps_response.py
vtpl_api/models/event_type.py
vtpl_api/models/evidence_config.py
vtpl_api/models/extra.py
vtpl_api/models/face_category.py
vtpl_api/models/face_event.py
vtpl_api/models/face_event_with_event_snaps.py
vtpl_api/models/face_event_with_registered_face_snaps.py
vtpl_api/models/face_events_response.py
vtpl_api-1.0.4.dist-info/LICENSE
vtpl_api-1.0.4.dist-info/METADATA
vtpl_api-1.0.4.dist-info/WHEEL
vtpl_api-1.0.4.dist-info/top_level.txt
vtpl_api-1.0.4.dist-info/RECORD
